AUTHORS.rst
LICENSE.txt
MANIFEST.in
README.rst
setup.py
django_rulez.egg-info/PKG-INFO
django_rulez.egg-info/SOURCES.txt
django_rulez.egg-info/dependency_links.txt
django_rulez.egg-info/not-zip-safe
django_rulez.egg-info/top_level.txt
rulez/__init__.py
rulez/backends.py
rulez/exceptions.py
rulez/models.py
rulez/registry.py
rulez/rolez/__init__.py
rulez/rolez/base.py
rulez/rolez/cache_helper.py
rulez/rolez/models.py
rulez/rolez/signals.py
rulez/templatetags/__init__.py
rulez/templatetags/rulez_perms.py
rulez/tests/__init__.py
rulez/tests/backend.py
rulez/tests/registry.py
rulez/tests/roles_helpers.py
rulez/tests/signals.py
rulez/tests/templatetags.py