Metadata-Version: 1.1
Name: django-rulez
Version: 1.0.1
Summary: A lean and mean object-level rules system for the Django framework
Home-page: http://github.com/chrisglass/django-rulez
Author: Christopher Glass
Author-email: tribaal@gmail.com
License: BSD
Keywords: authorization,backends,django,rules,permissions,rulez
Platform: UNKNOWN
Classifier: Programming Language :: Python
Classifier: Topic :: Software Development :: Libraries :: Python Modules
Classifier: Intended Audience :: Developers
Classifier: License :: OSI Approved :: BSD License
Classifier: Operating System :: OS Independent
Classifier: Framework :: Django
Classifier: Environment :: Web Environment
